MANIFEST.in
README.txt
mmlf_gui
run_mmlf
setup.cfg
setup.py
config/discrete_brio/world_td_lambda.yaml
config/double_pole_balancing/world.yaml
config/linear_markov_chain/world.yaml
config/maze2d/maze_non_stationary_complex.cfg
config/maze2d/maze_several_rooms.cfg
config/maze2d/maze_simple.cfg
config/maze2d/world_several_rooms_actor_critic.yaml
config/maze2d/world_several_rooms_dyna_td_prioritized_sweeping.yaml
config/maze2d/world_several_rooms_dyna_td_trajectory_sampling.yaml
config/maze2d/world_several_rooms_rmax_prioritized_sweeping.yaml
config/maze2d/world_several_rooms_td_lambda.yaml
config/maze_cliff/world_extended_td_lambda.yaml
config/maze_cliff/world_monte_carlo.yaml
config/maze_cliff/world_td_lambda.yaml
config/mountain_car/world_dps.yaml
config/mountain_car/world_dyna_td.yaml
config/mountain_car/world_fitted_r_max.yaml
config/mountain_car/world_mbdps.yaml
config/mountain_car/world_td_lambda_exploration.yaml
config/mountain_car/world_td_lambda_no_exploration.yaml
config/pinball_maze/world_hard_single_td_lambda.yaml
config/pinball_maze/world_simple_single_td_lambda.yaml
config/po_double_pole_balancing/world.yaml
config/single_pole_balancing/world_dps.yaml
doc/_build/html/genindex.html
doc/_build/html/index.html
doc/_build/html/objects.inv
doc/_build/html/py-modindex.html
doc/_build/html/search.html
doc/_build/html/searchindex.js
doc/_build/html/_downloads/mountain_car.zip
doc/_build/html/_downloads/test_experiment.zip
doc/_build/html/_images/current_experiment_results.png
doc/_build/html/_images/discrete_brio_viewer.png
doc/_build/html/_images/experiment_statistics.png
doc/_build/html/_images/experimenter.png
doc/_build/html/_images/gui_configure_popup.png
doc/_build/html/_images/gui_float_stream_viewer.png
doc/_build/html/_images/gui_main_window.png
doc/_build/html/_images/gui_maze_viewer.png
doc/_build/html/_images/inheritance44e94e4005.png
doc/_build/html/_images/inheritance4bc70b3af0.png
doc/_build/html/_images/inheritance959250a6bf.png
mmlf.egg-info/PKG-INFO
mmlf.egg-info/SOURCES.txt
mmlf.egg-info/dependency_links.txt
mmlf.egg-info/top_level.txt
