Metadata-Version: 1.0
Name: mmlf
Version: 1.0
Summary: The Maja Machine Learning Framework
Home-page: http://mmlf.sourceforge.net/
Author: Jan Hendrik Metzen, Mark Edgington
Author-email: jhm@informatik.uni-bremen.de
License: GPL
Download-URL: http://downloads.sourceforge.net/project/mmlf/mmlf/1.0/mmlf_1.0.tar.gz
Platform: any
Classifier: Programming Language :: Python
Classifier: Development Status :: 4 - Beta
Classifier: Environment :: Console
Classifier: Environment :: X11 Applications :: Qt
Classifier: Intended Audience :: Science/Research
Classifier: Intended Audience :: Education
Classifier: License :: OSI Approved :: GNU General Public License (GPL)
Classifier: Operating System :: OS Independent
Classifier: Topic :: Scientific/Engineering :: Artificial Intelligence
